snowflake/__init__.py
snowflake/snowflake.py
snowflake_tool-1.0.0.dist-info/LICENSE
snowflake_tool-1.0.0.dist-info/METADATA
snowflake_tool-1.0.0.dist-info/WHEEL
snowflake_tool-1.0.0.dist-info/top_level.txt
snowflake_tool-1.0.0.dist-info/RECORD
