Metadata-Version: 2.1
Name: snowflake-tool
Version: 1.0.0
Summary: Simple snowflake id generator
Home-page: https://github.com/novice2194/snowflake-tool
Author: novice2194
Author-email: 2194150786@qq.com
License: MIT
Keywords: python,snowflake,id generator
Classifier: Development Status :: 4 - Beta
Classifier: Intended Audience :: Developers
Classifier: License :: OSI Approved :: MIT License
Classifier: Programming Language :: Python :: 3
Classifier: Programming Language :: Python :: 3.7
Classifier: Programming Language :: Python :: 3.8
Classifier: Programming Language :: Python :: 3.9
Classifier: Programming Language :: Python :: 3.10
Classifier: Programming Language :: Python :: 3.11
Classifier: Operating System :: Unix
Classifier: Operating System :: MacOS :: MacOS X
Classifier: Operating System :: Microsoft :: Windows
License-File: LICENSE
